ml_helpers/__init__.py
ml_helpers/activations.py
ml_helpers/gradient_checking.py
ml_helpers/initializations.py
ml_helpers/propagate.py
ml_helpers/tests.py
ml_helpers/tf_helpers.py
ml_helpers/utils.py
ml_helpers/optimizations/__init__.py
ml_helpers/optimizations/adam.py
ml_helpers/optimizations/gradient_descent.py
ml_helpers/optimizations/momentum.py
ml_helpers/optimizations/random_mini_batches.py
ml_helpers/optimizations/tests.py
ml_helpers-0.0.22.dist-info/LICENSE
ml_helpers-0.0.22.dist-info/METADATA
ml_helpers-0.0.22.dist-info/WHEEL
ml_helpers-0.0.22.dist-info/top_level.txt
ml_helpers-0.0.22.dist-info/RECORD
