Metadata-Version: 2.1
Name: ml-helpers
Version: 0.0.22
Summary: Functions to help build machine learning tools
Home-page: https://github.com/cdevine49/ml_helpers
Author: Conor Devine
Author-email: conorjdevine@gmail.com
License: UNKNOWN
Platform: UNKNOWN
Classifier: Programming Language :: Python :: 3
Classifier: License :: OSI Approved :: MIT License
Classifier: Operating System :: OS Independent
